{
    "id": "bitcoin-freedom",
    "nome": "Bitcoin Freedom",
    "img": "/img/podcast/bitcoin-freedom.jpg",
    "apps": [
        {
            "app": "fountain",
            "url": "https://fountain.fm/show/GeOiZ3OrPLYBueqcRP7n"
        },
        {
            "app": "spotify",
            "url": "https://open.spotify.com/show/2RWKeiHLsJyLhf4AdVpGHH"
        },
        {
            "app": "amazon",
            "url": "https://music.amazon.it/podcasts/0f7a2f25-aa2b-4ebe-85ac-9965650fd263/bitcoin-freedom"
        },
        {
            "app": "podcast addict",
            "url": "https://podcastaddict.com/podcast/bitcoin-freedom/5052566"
        }
    ],
    "sito": "https://www.massmux.com/",
    "descrizione": "Bitcoin Freedom, il podcast di Massimo Musumeci, un fisico con una solida esperienza nel mondo della ricerca, ci porta la sua prospettiva unica, unendo la precisione scientifica all'analisi del mondo Bitcoin e della tecnologia dell'informazione. Con una laurea magistrale in fisica e la sua attuale posizione di ricercatore in Svizzera, Massimo offre una visione approfondita e informata su Bitcoin e su Lightning Network"
}