{
	"titoli": [
		{
			"id": 1,
			"url": "https:\/\/amzn.eu\/d\/7r7aQLn",
			"titolo": "Mastering Lightning Network",
			"sottotitolo": null,
			"autori": "Andreas Antonopoulos, O.Osuntokun, R.Pickhardt",
			"traduttore": "Riccardo Masutti",
			"data pubblicazione": 1677283200000,
			"anno": 2023
		},
		{
			"id": 2,
			"url": "https:\/\/amzn.eu\/d\/ijfByS8",
			"titolo": "Mastering Bitcoin",
			"sottotitolo": null,
			"autori": "Andreas M. Antonopoulos",
			"traduttore": "Riccardo Masutti",
			"data pubblicazione": 1565481600000,
			"anno": 2019
		},
		{
			"id": 3,
			"url": "https:\/\/amzn.eu\/d\/h7hsjyn",
			"titolo": "21 Lezioni",
			"sottotitolo": null,
			"autori": "Der Gigi",
			"traduttore": "Davide Milani",
			"data pubblicazione": 1636502400000,
			"anno": 2021
		},
		{
			"id": 4,
			"url": "https:\/\/www.amazon.it\/dp\/B0CH25H14X",
			"titolo": "21 Pensieri dal Villaggio Bitcoin",
			"sottotitolo": "Osservare il mondo alla rovescia attraverso una moneta sana e onesta",
			"autori": "Valerio Dalla Costa",
			"traduttore": null,
			"data pubblicazione": 1693612800000,
			"anno": 2023
		},
		{
			"id": 5,
			"url": "https:\/\/amzn.eu\/d\/5s4pE87",
			"titolo": "IL DENARO: Dalle Origini ai Nostri Giorni",
			"sottotitolo": "in 5 Minuti di Lettura, dai 5 Anni in Su",
			"autori": "Riccardo Siotto",
			"traduttore": null,
			"data pubblicazione": 1661904000000,
			"anno": 2022
		},
		{
			"id": 6,
			"url": "https:\/\/www.amazon.it\/dp\/B0CJKV58Y1",
			"titolo": "Il Vademecum Bitcoin",
			"sottotitolo": "Concetti Fondamentali di Economia, Tecnologia e Psicologia",
			"autori": "Anil Patel, Virginia Darcy",
			"traduttore": "Guybrush, Alevand",
			"data pubblicazione": 1695168000000,
			"anno": 2023
		},
		{
			"id": 7,
			"url": "https:\/\/amzn.eu\/d\/6ORrHxn",
			"titolo": "Villaggio Bitcoin",
			"sottotitolo": "L'alba di una nuova societ\u00e0 basata su una moneta sana e onesta",
			"autori": "Valerio Dalla Costa, Giacomo Zucco",
			"traduttore": null,
			"data pubblicazione": 1658275200000,
			"anno": 2022
		},
		{
			"id": 8,
			"url": "https:\/\/amzn.eu\/d\/f7bmsWV",
			"titolo": "Cos'\u00e8 il denaro, cos'\u00e8 il bitcoin",
			"sottotitolo": "Un viaggio tra storia e futuro",
			"autori": "Claudio Ferrari",
			"traduttore": null,
			"data pubblicazione": 1691366400000,
			"anno": 2023
		},
		{
			"id": 9,
			"url": "https:\/\/amzn.eu\/d\/dnRZJlY",
			"titolo": "Bitcoin Manuale Avanzato",
			"sottotitolo": "Sicurezza e Privacy, Strategie di Custodia, Errori Comuni, Lightning Network",
			"autori": "Marco Cattaneo, Claudia Marchione",
			"traduttore": null,
			"data pubblicazione": 1660435200000,
			"anno": 2022
		},
		{
			"id": 10,
			"url": "https:\/\/amzn.eu\/d\/8YBM4yT",
			"titolo": "Criptoeconomia: Principi Fondamentali Di Bitcoin",
			"sottotitolo": null,
			"autori": "Eric Voskuil",
			"traduttore": "Parsevalbtc",
			"data pubblicazione": 1663459200000,
			"anno": 2022
		},
		{
			"id": 11,
			"url": "https:\/\/amzn.eu\/d\/e8Ghwkl",
			"titolo": "Protocollo Bitcoin",
			"sottotitolo": "Fondamenti per capire la tecnologia delle criptovalute e le sue applicazioni",
			"autori": "Umberto Tarantino, Giacomo Zucco",
			"traduttore": null,
			"data pubblicazione": 1639008000000,
			"anno": 2021
		},
		{
			"id": 12,
			"url": "https:\/\/amzn.eu\/d\/dRhWmCf",
			"titolo": "Domande & risposte su Bitcoin",
			"sottotitolo": "Dal concetto di blockchain alla definizione della suite LNP\/BP",
			"autori": "David Coen ",
			"traduttore": null,
			"data pubblicazione": 1572393600000,
			"anno": 2019
		},
		{
			"id": 13,
			"url": "https:\/\/amzn.eu\/d\/h18cRWT",
			"titolo": "L'uomo pi\u00f9 ricco del mondo",
			"sottotitolo": "Un'indagine per scoprire chi \u00e8 Satoshi Nakamoto, l'ideatore di Bitcoin",
			"autori": "Gian Luca Comandini",
			"traduttore": null,
			"data pubblicazione": 1667865600000,
			"anno": 2022
		},
		{
			"id": 14,
			"url": "https:\/\/amzn.eu\/d\/f7dn1Zq",
			"titolo": "Bitcoin 199 domande",
			"sottotitolo": "Bitcoin In Action Vol. 3",
			"autori": "Alessio Barnini, Alessandro Aglietti",
			"traduttore": null,
			"data pubblicazione": 1562198400000,
			"anno": 2019
		},
		{
			"id": 15,
			"url": "https:\/\/amzn.eu\/d\/9tsBPAZ",
			"titolo": "Bitcoin Guida Facile",
			"sottotitolo": "Manuale Base, Investimenti Finanziari, Blockchain, Criptovalute",
			"autori": "Marco Cattaneo, Claudia Marchione",
			"traduttore": null,
			"data pubblicazione": 1639958400000,
			"anno": 2021
		},
		{
			"id": 16,
			"url": "https:\/\/amzn.eu\/d\/59mf8H7",
			"titolo": "Bitcoin In Action",
			"sottotitolo": "SegWit, Bitcoin Script & Smart Contracts",
			"autori": "Alessio Barnini, Alessandro Aglietti",
			"traduttore": null,
			"data pubblicazione": 1605484800000,
			"anno": 2020
		},
		{
			"id": 17,
			"url": "https:\/\/amzn.eu\/d\/6nbnF2G",
			"titolo": "Dal sesterzio al Bitcoin",
			"sottotitolo": "Vecchie e nuove dimensioni del denaro",
			"autori": "Angelo Miglietta, Alberto Mingardi",
			"traduttore": null,
			"data pubblicazione": 1581552000000,
			"anno": 2020
		},
		{
			"id": 18,
			"url": "https:\/\/amzn.eu\/d\/7AQEArn",
			"titolo": "Mamma, ho comprato Bitcoin!",
			"sottotitolo": "Un manuale semplice e completo per tutte le mamme (e pap\u00e0, zii, fratelli) che ancora ci guardano stupiti quando parliamo di Bitcoin",
			"autori": "Lorenzo Primiterra",
			"traduttore": null,
			"data pubblicazione": 1618617600000,
			"anno": 2021
		},
		{
			"id": 19,
			"url": "https:\/\/amzn.eu\/d\/cyGsSFD",
			"titolo": "Avere o Non Avere Bitcoin, questo \u00e8 il problema..per chi non ne ha",
			"sottotitolo": "Capire, Acquistare e Custodire Criptovalute per Principianti",
			"autori": "Bruno Luppino Muratore",
			"traduttore": null,
			"data pubblicazione": 1712793600000,
			"anno": 2024
		},
		{
			"id": 20,
			"url": "https:\/\/amzn.eu\/d\/9lF1RGS",
			"titolo": "Breve saggio esplicativo su bitcoin e blockchain",
			"sottotitolo": "Per non esperti ma curiosi",
			"autori": "Francesco Basso",
			"traduttore": null,
			"data pubblicazione": 1710374400000,
			"anno": 2024
		},
		{
			"id": 21,
			"url": "https:\/\/amzn.eu\/d\/5AcdIQP",
			"titolo": "Bitcoin e criptovalute: da zero a esperto",
			"sottotitolo": null,
			"autori": "Satoshi Rocco",
			"traduttore": null,
			"data pubblicazione": 1707955200000,
			"anno": 2024
		},
		{
			"id": 22,
			"url": "https:\/\/amzn.eu\/d\/9OZppzs",
			"titolo": "Beyond the halving bitcoin",
			"sottotitolo": "Un viaggio nell'evoluzione bitcoin",
			"autori": "The Bull Academy",
			"traduttore": null,
			"data pubblicazione": 1700179200000,
			"anno": 2023
		},
		{
			"id": 23,
			"url": "https:\/\/amzn.eu\/d\/0fs2al7",
			"titolo": "Il successo dei bitcoin (Layered money)",
			"sottotitolo": "Capire facilmente l\u2019evoluzione della moneta e l\u2019importanza dei bitcoin",
			"autori": "Nik Bhatia",
			"traduttore": "Carlo De Benedittis",
			"data pubblicazione": 1692316800000,
			"anno": 2023
		},
		{
			"id": 24,
			"url": "https:\/\/amzn.eu\/d\/5pEsLdD",
			"titolo": "Cos\u2019\u00e9 il Bitcoin per ragazzi e adulti",
			"sottotitolo": "Il Mondo digitale del Bitcoin",
			"autori": "Phantom Ultimo",
			"traduttore": null,
			"data pubblicazione": 1685318400000,
			"anno": 2023
		},
		{
			"id": 25,
			"url": "https:\/\/amzn.eu\/d\/5rGZjpF",
			"titolo": "Bitcoin & Libert\u00e0 Esponenziale",
			"sottotitolo": "Perch\u00e9 Bitcoin \u00e8 l'eccellenza monetaria e perch\u00e9 l'uso di Bitcoin porter\u00e0 alla pace globale, al progresso della civilt\u00e0 e alla libert\u00e0 esponenziale",
			"autori": "Jake Leary",
			"traduttore": "Milano Trustless",
			"data pubblicazione": 1667952000000,
			"anno": 2022
		},
		{
			"id": 26,
			"url": "https:\/\/amzn.eu\/d\/iFcLhwU",
			"titolo": "Dizionario Bitcoin - Italiano",
			"sottotitolo": "Glossario ragionato sul mondo Bitcoin per i meno esperti",
			"autori": "Davide Carboni",
			"traduttore": null,
			"data pubblicazione": 1407196800000,
			"anno": 2014
		},
		{
			"id": 27,
			"url": "https:\/\/amzn.eu\/d\/cGipgle",
			"titolo": "Adozione di Bitcoin come moneta legale in El Salvador",
			"sottotitolo": "Analisi della strategia di implementazione",
			"autori": "Francisco Sorto Rivas",
			"traduttore": null,
			"data pubblicazione": 1650758400000,
			"anno": 2022
		}
	]
}