{"id":23,"nome":"Phoenix","web site":"https:\/\/phoenix.acinq.co\/","appgallery huawei":null,"fdroid":null,"apk direct download":null,"twitter":"PhoenixWallet","nostr":null,"reddit":null,"telegram":null,"facebook":null,"instagram":null,"linkedin":null,"discord":null,"selfcustodial":"s","custodial":null,"open source":"s","per iniziare":"s","livello":"intermedio","lightning":"s","Bolt12":"s","Desktop":null,"Windows":null,"MacOS":null,"Linux":null,"iOS":"s","Android":"s","Web browser":null,"Riproducibile":"n","walletscrutiny-desktop":null,"walletscrutiny-android":"fr.acinq.phoenix.mainnet","walletscrutiny-iphone":"co.acinq.phoenix","Connessione nodo":null,"Coin Control":null,"Tor":"s","CoinJoin":"s","Fee Control":null,"Bech32":"s","Testnet":"s","Multisig":"s","Taproot":"s","Taproot.1":"s","Payjoin P2EP":"s","Batching":null,"RBF":"s","CPFP":null,"PSBT":null,"Passphrase":null,"BIP-32":null,"BIP-39":"s","BIP-44":null,"BIP-47":null,"BIP-49":null,"BIP-85":null,"RAW tx":null,"Signing Messages":null,"SPV":null,"Connessione hardware":null,"Miniscript":null,"Swap":"s","AMP":null,"Wumbo":null,"Trampoline payments":null,"LNURL":"s","LNURL-p":null,"LNURL-w":null,"URI Scheme":null,"Submarine swap":null,"silent payment ":null}